ce_detector/__init__.py
ce_detector/__main__.py
ce_detector/annotator.py
ce_detector/async_version.py
ce_detector/chromosome.yml
ce_detector/cli.py
ce_detector/detector.py
ce_detector/main.py
ce_detector/scanner.py
ce_detector/utils.py
ce_detector-0.2.1.dist-info/AUTHORS.rst
ce_detector-0.2.1.dist-info/LICENSE
ce_detector-0.2.1.dist-info/METADATA
ce_detector-0.2.1.dist-info/WHEEL
ce_detector-0.2.1.dist-info/entry_points.txt
ce_detector-0.2.1.dist-info/top_level.txt
ce_detector-0.2.1.dist-info/RECORD
