Metadata-Version: 2.1
Name: ce-detector
Version: 0.2.1
Summary: A program used to detect Cryptic Exon.
Home-page: https://github.com/cauliyang/ce_detector/
Author: YangyangLi
Author-email: li002252@umn.edu
License: MIT
Platform: UNKNOWN
Classifier: License :: OSI Approved :: MIT License
Classifier: Programming Language :: Python
Classifier: Programming Language :: Python :: 3
Classifier: Programming Language :: Python :: 3.6
Classifier: Programming Language :: Python :: Implementation :: CPython
Classifier: Programming Language :: Python :: Implementation :: PyPy
Requires-Python: >=3.6.0
Requires-Dist: click (~=7.1.2)
Requires-Dist: gffutils (~=0.10.1)
Requires-Dist: importlib-resources (~=4.1.0)
Requires-Dist: numpy (~=1.19.4)
Requires-Dist: pandas (~=1.2.0)
Requires-Dist: pysam (~=0.16.0.1)
Requires-Dist: pytest (~=5.4.3)
Requires-Dist: rich (~=9.6.1)
Requires-Dist: setuptools (~=50.3.0)
Requires-Dist: pyyaml (==5.3.1)
